pygifconvb_test_kang/__init__.py
pygifconvb_test_kang/converter.py
pygifconvb_test_kang-1.0.0.dist-info/LICENSE
pygifconvb_test_kang-1.0.0.dist-info/METADATA
pygifconvb_test_kang-1.0.0.dist-info/WHEEL
pygifconvb_test_kang-1.0.0.dist-info/top_level.txt
pygifconvb_test_kang-1.0.0.dist-info/RECORD
